attributes_serializer/__init__.py
attributes_serializer/sale_prices_serializer.py
attributes_serializer-1.0.1.dist-info/METADATA
attributes_serializer-1.0.1.dist-info/WHEEL
attributes_serializer-1.0.1.dist-info/top_level.txt
attributes_serializer-1.0.1.dist-info/RECORD
