Metadata-Version: 2.1
Name: attributes_serializer
Version: 1.0.1
Summary: Module to interact with marketplaces
Author: derijabyla
Author-email: dulugov@gmail.com
